{
    "growth_layer": [
        {
            "name": "Sproutling",
            "hp": 32,
            "intents": [
                "Attack 6",
                "Attack 6",
                "Buff (+2 Block, Gain Thorns 1)"
            ],
            "special": "Gains Thorns 1 when buffing"
        },
        {
            "name": "Spore Puffer",
            "hp": 30,
            "intents": [
                "Debuff (2 Poison)",
                "Attack 4",
                "Debuff (2 Poison)",
                "Rest"
            ],
            "special": "On death, apply +1 Poison to all enemies"
        },
        {
            "name": "Vine Shooter",
            "hp": 35,
            "intents": [
                "Attack 5",
                "Block 8",
                "Attack 5 + Apply Weak"
            ],
            "special": "Every third Attack applies Weak 1 for 2 turns"
        },
        {
            "name": "Barkshield",
            "hp": 30,
            "intents": [
                "Block 12",
                "Attack 8",
                "Block 12",
                "Attack 8"
            ],
            "special": "Gains +3 Block when taking unblocked damage"
        },
        {
            "name": "Sap Warden",
            "hp": 34,
            "intents": [
                "Buff Ally (Heal 4)",
                "Attack 4",
                "Buff All Allies (+2 Block)",
                "Attack 4"
            ],
            "special": "Heals 2 HP to a random ally on attack"
        }
    ],
    "decay_layer": [
        {
            "name": "Rot Crawler",
            "hp": 35,
            "intents": [
                "Attack 7 + Apply Decay 1",
                "Attack 7",
                "Rest"
            ],
            "special": "Decay reduces Max HP by 1 per stack"
        },
        {
            "name": "Mold Spitter",
            "hp": 32,
            "intents": [
                "Debuff (2 Weak)",
                "Attack 6",
                "Debuff (2 Vulnerable)",
                "Rest"
            ],
            "special": "On turn 4, also applies 1 Chill"
        },
        {
            "name": "Bone Husk",
            "hp": 36,
            "intents": [
                "Block 15",
                "Taunt + Attack 10",
                "Block 15",
                "Attack 10"
            ],
            "special": "Immune to Stun and Poison; taunt forces targeting"
        },
        {
            "name": "Sludge Fiend",
            "hp": 34,
            "intents": [
                "Attack 5 + Apply Slow",
                "Attack 5",
                "Debuff (Apply 1 Weak to all)"
            ],
            "special": "Slow reduces card draw by 1 next turn"
        },
        {
            "name": "Decay Caller",
            "hp": 20,
            "intents": [
                "Buff Allies (+1 Decay on hits)",
                "Rest",
                "Buff Allies",
                "Attack 4"
            ],
            "special": "Allies deal +1 Decay on hit while buff is active"
        }
    ],
    "elemental_layer": [
        {
            "name": "Flame Wisp",
            "hp": 35,
            "intents": [
                "Debuff (3 Burn)",
                "Rest",
                "Attack 7",
                "Rest"
            ],
            "special": "Burn deals 2 damage at the start of your turn"
        },
        {
            "name": "Water Sprite",
            "hp": 32,
            "intents": [
                "Attack 4 + Heal 3",
                "Rest",
                "Attack 4 + Heal 3",
                "Rest"
            ],
            "special": "Heals self when attacking"
        },
        {
            "name": "Stone Golem",
            "hp": 42,
            "intents": [
                "Block 12",
                "Attack 12",
                "Block 12",
                "Attack 12"
            ],
            "special": "When it blocks, gains extra 5 Block next turn"
        },
        {
            "name": "Storm Imp",
            "hp": 24,
            "intents": [
                "Attack 6 + Stun 1",
                "Rest",
                "Attack 6 + Stun 1",
                "Rest"
            ],
            "special": "Stun skips your next card-play turn"
        },
        {
            "name": "Rune Binder",
            "hp": 26,
            "intents": [
                "Debuff (Random: Weak/Vulnerable/Burn)",
                "Buff Self (+3 Block)",
                "Attack 5",
                "Rest"
            ],
            "special": "Picks a new debuff each cycle"
        }
    ],
    "elite": [
        {
            "name": "Corrupted Ent",
            "hp": 80,
            "intents": [
                "Attack 10",
                "Buff (+5 Block, Thorns 2)",
                "Attack 15 + Apply Weak"
            ],
            "special": "Thorns damage increases by 1 each turn"
        },
        {
            "name": "Rot Knight",
            "hp": 85,
            "intents": [
                "Attack 12",
                "Block 15",
                "Attack 8 + Apply Decay 2"
            ],
            "special": "Start combat with 2 Artifact"
        }
    ],
    "boss": [
        {
            "name": "Withering Sentinel",
            "hp": 210,
            "intents": [
                "Attack 8",
                "Buff (+2 Strength)",
                "Attack 12"
            ],
            "special": "Passive: Takes +1 damage per Seed you have. Phase 2: Applies Anti-Heal.",
            "archetype_counter": "growth"
        },
        {
            "name": "Purifier Construct",
            "hp": 220,
            "intents": [
                "Attack 6",
                "Debuff (Cleanse Player Poison)",
                "Attack 10 + Block 10"
            ],
            "special": "Every 4 turns: Cleanses ALL Poison from self. Takes reduced DoT.",
            "archetype_counter": "decay"
        },
        {
            "name": "Bulwark Colossus",
            "hp": 230,
            "intents": [
                "Block 20",
                "Attack 15",
                "Rest"
            ],
            "special": "Shield refreshes if hit >3 times/turn. Weak once broken.",
            "archetype_counter": "elemental"
        }
    ],
    "boss_act2": [
        {
            "name": "Gravebloom Behemoth",
            "hp": 220,
            "intents": [
                "Attack 15",
                "Attack 5 + Apply Constrict/Slow",
                "Buff Self (Heal 20)"
            ],
            "special": "Start of Turn: Gains +1 Str if you have ≥10 Block (+2 if ≥20). Phase 2: Ignores Block.",
            "archetype_counter": "growth",
            "tier": "boss"
        },
        {
            "name": "Carrion Feeder",
            "hp": 210,
            "intents": [
                "Attack 8 x 2",
                "Debuff (3 Vulnerable)",
                "Attack 20 + Heal"
            ],
            "special": "Reflects 2 damage the FIRST time it takes Poison damage per turn.",
            "archetype_counter": "decay",
            "tier": "boss"
        },
        {
            "name": "Stormwarden",
            "hp": 210,
            "intents": [
                "Attack 12 + Apply Shock",
                "Block 30",
                "Attack 5 + Drain Energy"
            ],
            "special": "Static Field: Cards give Static (Strike=1, Tactic=0, Ritual=2). At 5 Static: Take 10 Dmg + Reset.",
            "archetype_counter": "elemental",
            "tier": "boss"
        }
    ],
    "boss_act3": [
        {
            "name": "World Reclaimer",
            "hp": 225,
            "intents": [
                "Attack 20",
                "Block 40 + Apply Constrict",
                "Attack 10 x 2"
            ],
            "special": "Seed Harvest: End of Turn, if Seeds > 5, consumes excess. Heals 5 HP per seed + Gains Str.",
            "archetype_counter": "growth",
            "tier": "boss"
        },
        {
            "name": "Eternal Arbiter",
            "hp": 235,
            "intents": [
                "Attack 15 + Apply Frail",
                "Attack (Missing HP as Dmg)",
                "Buff (+2 Strength, Purge Buffs)"
            ],
            "special": "Equilibrium: Poison Damage has diminishing returns (>20: 50%, >30: 20%).",
            "archetype_counter": "decay",
            "tier": "boss"
        },
        {
            "name": "Chronoshard",
            "hp": 235,
            "intents": [
                "Attack 3 x 5",
                "Heal 30 (Rewind)",
                "Attack 10 + Stun"
            ],
            "special": "Temporal Stress: Card plays gain Stress (Strike=1, Ritual=2). At 6: Take 12 Dmg + Reset.",
            "archetype_counter": "elemental",
            "tier": "boss"
        }
    ]
}